mantik/__init__.py
mantik/authentication/__init__.py
mantik/authentication/api.py
mantik/authentication/auth.py
mantik/authentication/tokens.py
mantik/cli/__init__.py
mantik/cli/_callbacks.py
mantik/cli/_options.py
mantik/cli/data/__init__.py
mantik/cli/data/data.py
mantik/cli/init.py
mantik/cli/main.py
mantik/cli/models/__init__.py
mantik/cli/models/models.py
mantik/cli/remote_file_service/__init__.py
mantik/cli/remote_file_service/_arguments.py
mantik/cli/remote_file_service/_options.py
mantik/cli/remote_file_service/s3_file_service.py
mantik/cli/remote_file_service/unicore_file_service.py
mantik/cli/runs/__init__.py
mantik/cli/runs/_options.py
mantik/cli/runs/local.py
mantik/cli/runs/runs.py
mantik/cli/runs/submit.py
mantik/cli/utils.py
mantik/config/__init__.py
mantik/config/_base.py
mantik/config/_utils.py
mantik/config/core.py
mantik/config/environment.py
mantik/config/exceptions.py
mantik/config/executable.py
mantik/config/firecrest.py
mantik/config/read.py
mantik/config/resources.py
mantik/config/ssh_remote_compute_system.py
mantik/config/validate.py
mantik/data_repository/__init__.py
mantik/data_repository/data_repository.py
mantik/init.py
mantik/mlflow.py
mantik/models/__init__.py
mantik/models/image.py
mantik/py.typed
mantik/remote_file_service/__init__.py
mantik/remote_file_service/abstract_file_service.py
mantik/remote_file_service/data_client.py
mantik/remote_file_service/s3_file_service.py
mantik/remote_file_service/unicore_file_service.py
mantik/runs/__init__.py
mantik/runs/artifacts.py
mantik/runs/local.py
mantik/runs/mlflow_monkeypatch.py
mantik/runs/notebook.py
mantik/runs/remote.py
mantik/runs/schemas.py
mantik/testing/__init__.py
mantik/testing/cognito.py
mantik/testing/config.py
mantik/testing/env.py
mantik/testing/firecrest.py
mantik/testing/mlflow_server.py
mantik/testing/pyunicore.py
mantik/testing/remote_file_service.py
mantik/testing/requests.py
mantik/testing/stress.py
mantik/testing/token.py
mantik/tracking/__init__.py
mantik-0.5.11.dist-info/LICENSE
mantik-0.5.11.dist-info/METADATA
mantik-0.5.11.dist-info/WHEEL
mantik-0.5.11.dist-info/entry_points.txt
mantik-0.5.11.dist-info/RECORD
