Metadata-Version: 2.1
Name: mantik
Version: 0.5.11
Summary: mantik for mlflow
Home-page: https://mantik.ai/
License: MIT
Keywords: mlflow,machine learning,hpc,unicore
Author: Fabian Emmerich
Author-email: fabian.emmerich@4-cast.de
Maintainer: Elia Boscaini
Maintainer-email: elia.boscaini@ambrosys.de
Requires-Python: >=3.9,<4.0
Classifier: Intended Audience :: Developers
Classifier: Intended Audience :: Science/Research
Classifier: License :: OSI Approved :: MIT License
Classifier: Programming Language :: Python :: 3
Classifier: Programming Language :: Python :: 3.9
Classifier: Programming Language :: Python :: 3.10
Classifier: Programming Language :: Python :: 3.11
Classifier: Programming Language :: Python :: 3.12
Classifier: Topic :: Scientific/Engineering :: Artificial Intelligence
Classifier: Topic :: Software Development :: Libraries :: Python Modules
Provides-Extra: all
Provides-Extra: docker
Provides-Extra: mlflow
Provides-Extra: s3
Provides-Extra: unicore
Requires-Dist: PyYAML (>=6.0,<7.0)
Requires-Dist: click (>=8.1.3,<9.0.0)
Requires-Dist: docker (>=6.1.3,<7.0.0) ; extra == "docker"
Requires-Dist: dvc-s3 (>=3.2.0,<4.0.0)
Requires-Dist: fs (>=2.4.16,<3.0.0)
Requires-Dist: fs-s3fs (>=1.1.1,<2.0.0) ; extra == "s3" or extra == "all"
Requires-Dist: gitpython (>=3.1.43,<4.0.0)
Requires-Dist: gputil (>=1.4.0,<2.0.0)
Requires-Dist: ipython (==8.18.1)
Requires-Dist: mlflow-skinny (==2.2.2) ; extra == "mlflow" or extra == "all"
Requires-Dist: paramiko (>=3.4.1,<4.0.0)
Requires-Dist: psutil (>=5.9.6,<6.0.0)
Requires-Dist: py-cpuinfo (>=9.0.0,<10.0.0)
Requires-Dist: pyfirecrest (>=2.2.0,<3.0.0)
Requires-Dist: python-jose (>=3.3.0,<4.0.0)
Requires-Dist: pyunicore[crypto,fuse] (>=0.15.0,<0.16.0) ; extra == "unicore" or extra == "all"
Requires-Dist: requests (>=2.27.1,<3.0.0)
Requires-Dist: ruamel-yaml (>=0.18.6,<0.19.0)
Project-URL: Documentation, https://mantik-ai.gitlab.io/mantik
Project-URL: Repository, https://gitlab.com/mantik-ai/mantik
